rebasin/__init__.py
rebasin/interpolation.py
rebasin/merge_many.py
rebasin/model_info.py
rebasin/modules.py
rebasin/paths.py
rebasin/permutation_coordinate_descent.py
rebasin/permutation_initializer.py
rebasin/type_definitions.py
rebasin/utils.py
rebasin-0.0.47.dist-info/LICENSE
rebasin-0.0.47.dist-info/METADATA
rebasin-0.0.47.dist-info/WHEEL
rebasin-0.0.47.dist-info/top_level.txt
rebasin-0.0.47.dist-info/RECORD
