Metadata-Version: 2.1
Name: rebasin
Version: 0.0.47
Summary: An implementation of methods described in Git Re-basin-paper by Ainsworth et al.
Home-page: https://github.com/snimu/rebasin
Author: Sebastian Müller @snimu
Author-email: sebastian.nicolas.mueller@gmail.com
License: MIT
Keywords: torch git-rebasin rebasin interpolate interpolation model deep-learning
Classifier: License :: OSI Approved :: MIT License
Classifier: Operating System :: OS Independent
Classifier: Programming Language :: Python :: 3
Classifier: Programming Language :: Python :: 3 :: Only
Classifier: Programming Language :: Python :: 3.8
Classifier: Programming Language :: Python :: 3.9
Classifier: Programming Language :: Python :: 3.10
Classifier: Programming Language :: Python :: 3.11
Requires-Python: >=3.8
License-File: LICENSE
Requires-Dist: torch
Requires-Dist: numpy
Requires-Dist: scipy
Requires-Dist: tqdm
Requires-Dist: graphviz
Requires-Dist: torchview
